.gitignore
setup.py
ebs/__init__.py
ebs/linuxnode/__init__.py
ebs/linuxnode/bgsequence/__init__.py
ebs/linuxnode/bgsequence/basic.py
ebs/linuxnode/bgsequence/importer.py
ebs/linuxnode/bgsequence/mixin.py
ebs/linuxnode/bgsequence/models.py
ebs/linuxnode/bgsequence/persistence.py
ebs_linuxnode_bgsequence.egg-info/PKG-INFO
ebs_linuxnode_bgsequence.egg-info/SOURCES.txt
ebs_linuxnode_bgsequence.egg-info/dependency_links.txt
ebs_linuxnode_bgsequence.egg-info/requires.txt
ebs_linuxnode_bgsequence.egg-info/top_level.txt
example/app.py
example/image.jpg
example/node.py
example/pdf.pdf
example/run.py
example/video-2.mp4
example/video.mp4